fastapi_jwt_harmony/__init__.py
fastapi_jwt_harmony/base.py
fastapi_jwt_harmony/config.py
fastapi_jwt_harmony/constants.py
fastapi_jwt_harmony/dependencies.py
fastapi_jwt_harmony/exceptions.py
fastapi_jwt_harmony/fastapi_auth.py
fastapi_jwt_harmony/py.typed
fastapi_jwt_harmony/utils.py
fastapi_jwt_harmony/version.py
fastapi_jwt_harmony/websocket_auth.py
fastapi_jwt_harmony-0.2.1.dist-info/METADATA
fastapi_jwt_harmony-0.2.1.dist-info/WHEEL
fastapi_jwt_harmony-0.2.1.dist-info/licenses/LICENSE
fastapi_jwt_harmony-0.2.1.dist-info/RECORD
