Metadata-Version: 2.4
Name: fastapi-jwt-harmony
Version: 0.2.1
Summary: FastAPI JWT authentication library with Pydantic integration - bringing harmony to your auth flow
Project-URL: Homepage, https://github.com/ivolnistov/fastapi-jwt-harmony
Project-URL: Documentation, https://github.com/ivolnistov/fastapi-jwt-harmony/blob/main/docs/README.md
Project-URL: Repository, https://github.com/ivolnistov/fastapi-jwt-harmony
Project-URL: Bug Tracker, https://github.com/ivolnistov/fastapi-jwt-harmony/issues
Project-URL: Changelog, https://github.com/ivolnistov/fastapi-jwt-harmony/blob/main/CHANGELOG.md
Author-email: Ilya Volnistov <i.volnistov@gaijin.team>
Maintainer-email: Ilya Volnistov <i.volnistov@gaijin.team>
License-File: LICENSE
Keywords: authentication,fastapi,fastapi-jwt,harmony,jwt,pydantic
Classifier: Development Status :: 5 - Production/Stable
Classifier: Framework :: FastAPI
Classifier: License :: OSI Approved :: MIT License
Classifier: Operating System :: OS Independent
Classifier: Programming Language :: Python :: 3
Classifier: Programming Language :: Python :: 3.11
Classifier: Programming Language :: Python :: 3.12
Classifier: Programming Language :: Python :: 3.13
Classifier: Topic :: Internet :: WWW/HTTP :: HTTP Servers
Classifier: Topic :: Security
Classifier: Topic :: Software Development :: Libraries :: Python Modules
Requires-Python: >=3.11
Requires-Dist: fastapi
Requires-Dist: pydantic>=2.0
Requires-Dist: pyjwt>=2.10.1
Provides-Extra: asymmetric
Requires-Dist: cryptography>=2.6; extra == 'asymmetric'
